mercury_ocip/__init__.py
mercury_ocip/agent.py
mercury_ocip/client.py
mercury_ocip/exceptions.py
mercury_ocip/requester.py
mercury_ocip/automate/__init__.py
mercury_ocip/automate/alias_finder.py
mercury_ocip/automate/automation_tasks.py
mercury_ocip/automate/base_automation.py
mercury_ocip/automate/group_auditor.py
mercury_ocip/automate/user_digest.py
mercury_ocip/bulk/__init__.py
mercury_ocip/bulk/administrator.py
mercury_ocip/bulk/auto_attendant.py
mercury_ocip/bulk/base_operation.py
mercury_ocip/bulk/bulk_operations.py
mercury_ocip/bulk/call_center.py
mercury_ocip/bulk/call_pickup.py
mercury_ocip/bulk/device.py
mercury_ocip/bulk/hunt_group.py
mercury_ocip/bulk/user.py
mercury_ocip/commands/__init__.py
mercury_ocip/commands/base_command.py
mercury_ocip/commands/commands.py
mercury_ocip/libs/__init__.py
mercury_ocip/libs/basic_types.py
mercury_ocip/libs/types.py
mercury_ocip/plugins/__init__.py
mercury_ocip/plugins/base_plugin.py
mercury_ocip/utils/__init__.py
mercury_ocip/utils/defines.py
mercury_ocip/utils/file_handler.py
mercury_ocip/utils/parser.py
mercury_ocip/utils/shared_operations.py
mercury_ocip-1.0.1.dist-info/licenses/LICENSE
mercury_ocip-1.0.1.dist-info/METADATA
mercury_ocip-1.0.1.dist-info/WHEEL
mercury_ocip-1.0.1.dist-info/top_level.txt
mercury_ocip-1.0.1.dist-info/RECORD
