Metadata-Version: 2.4
Name: mercury-ocip
Version: 1.0.1
Summary: Python SDK for BroadWorks OCI (Open Client Interface) API
Author-email: Jordan Prescott <devteam@fourteenip.com>, Michael Clarke <devteam@fourteenip.com>, Billy Kelly <devteam@fourteenip.com>
License: MIT License
Keywords: broadworks,oci,soap,telephony,voip,sdk,api,mercury
Classifier: Development Status :: 5 - Production/Stable
Classifier: Intended Audience :: Developers
Classifier: Intended Audience :: System Administrators
Classifier: License :: OSI Approved :: MIT License
Classifier: Programming Language :: Python
Classifier: Programming Language :: Python :: 3
Classifier: Programming Language :: Python :: 3.12
Classifier: Programming Language :: Python :: 3.13
Classifier: Operating System :: OS Independent
Classifier: Topic :: Software Development :: Libraries :: Python Modules
Classifier: Topic :: Communications :: Telephony
Classifier: Topic :: Software Development :: Libraries
Classifier: Topic :: Utilities
Requires-Python: >=3.12
License-File: LICENSE
Requires-Dist: asyncio>=3.4.3
Requires-Dist: attrs>=21.4.0
Requires-Dist: httpx>=0.28.1
Requires-Dist: pydantic>=2.11.7
Requires-Dist: requests>=2.32.3
Requires-Dist: zeep>=4.3.1
Requires-Dist: types-lxml>=2025.3.30
Requires-Dist: lxml-stubs>=0.5.1
Requires-Dist: xmltodict>=1.0.2
Dynamic: license-file
